si_cli/__init__.py
si_cli/si_cli.py
si_cli-0.0.1.dist-info/METADATA
si_cli-0.0.1.dist-info/WHEEL
si_cli-0.0.1.dist-info/entry_points.txt
si_cli-0.0.1.dist-info/top_level.txt
si_cli-0.0.1.dist-info/RECORD
