Metadata-Version: 2.1
Name: si-cli
Version: 0.0.1
Summary: convert resistor and capacitor values from and to 3 digit codes(si format)
Home-page: https://github.com/ljurk/si_cli
Author: Lukas Jurk
Author-email: ljurk@pm.me
License: GPLv3
Keywords: resistor cap capacitor digit si
Platform: UNKNOWN
Classifier: Programming Language :: Python :: 3
Requires-Dist: Click
Requires-Dist: si-prefix
